{
    "twitter": {
        "use": false,
        "appKey": "",
        "appSecret": "",
        "accessToken": "",
        "accessSecret": "",
        "mimeTypes": ["image/png", "image/jpeg", "image/webp", "image/bmp", "image/gif", "video/mp4", "video/quicktime", "video/x-m4v"]
    },
    "bluesky": {
        "use": false,
        "handle": "handle.bsky.social",
        "appPassword": "",
        "refreshIntervalMs": 1800000,
        "mimeTypes": ["image/png", "image/jpeg", "image/webp", "image/avif", "image/bmp"]
    },
    "threads": {
        "use": false,
        "email": "can.be.same.as@instagram.com",
        "password": "",
        "mimeTypes": ["image/png", "image/jpeg", "video/mp4", "video/quicktime"]
    },
    "instagram": {
        "use": false,
        "email": "can.be.same.as@threads.net",
        "password": "",
        "mimeTypes": ["image/png", "image/jpeg", "image/heic", "image/heif", "video/mp4", "video/quicktime"]
    },
    "tumblr": {
        "use": false,
        "consumerKey": "",
        "consumerSecret": "",
        "blog": "bloghandle",
        "refreshIntervalMs": 1800000,
        "mimeTypes": ["image/png", "image/jpeg", "image/webp", "image/gif", "video/mp4", "video/quicktime", "audio/mpeg"]
    },
    "mastodon": {
        "use": false,
        "instance": "mastodon.instance",
        "accessToken": "",
        "mimeTypes": [
            "image/png",
            "image/jpeg",
            "image/gif",
            "image/webp",
            "image/heic",
            "image/heif",
            "image/avif",
            "video/mp4",
            "video/quicktime",
            "video/webm",
            "video/x-ms-asf",
            "video/ogg",
            "audio/webm",
            "audio/wave",
            "audio/wav",
            "audio/x-wav",
            "audio/x-pn-wave",
            "audio/vnd.wave",
            "audio/ogg",
            "audio/vorbis",
            "audio/mpeg",
            "audio/mp3",
            "audio/flac",
            "audio/aac",
            "audio/m4a",
            "audio/x-m4a",
            "audio/mp4",
            "audio/3gpp",
            "audio/opus"
        ]
    },
    "cohost": {
        "use": false,
        "email": "bla@email.com",
        "password": "",
        "handle": "handle",
        "mimeTypes": ["image/png", "image/jpeg", "image/gif","image/webp", "image/svg+xml", "audio/aac", "audio/mp4", "audio/x-m4a", "audio/flac", "audio/x-flac", "audio/mpeg", "audio/wav"]
    },
    "firefish": {
        "use": false,
        "instance": "firefish.instance",
        "token": ""
    },
    "userAgent": "shycatbot (https://github.com/whakama/shycatbot-open)",
    "scrapingUserAgent": "Mozilla/5.0 (Windows NT 10.0; Win64; x64; rv:109.0) Gecko/20100101 Firefox/120.0",
    "syncPosts": false,
    "priorityList": ["twitter", "tumblr", "bluesky", "mastodon", "firefish", "cohost", "threads", "instagram"],
    "directory": "/path/to/pictures",
    "postIntervalMs": 3600000
}